newchain_keys/__init__.py
newchain_keys/constants.py
newchain_keys/datatypes.py
newchain_keys/exceptions.py
newchain_keys/main.py
newchain_keys/validation.py
newchain_keys/backends/__init__.py
newchain_keys/backends/base.py
newchain_keys/backends/coincurve.py
newchain_keys/backends/native/__init__.py
newchain_keys/backends/native/ecdsa.py
newchain_keys/backends/native/jacobian.py
newchain_keys/backends/native/main.py
newchain_keys/tools/__init__.py
newchain_keys/tools/factories.py
newchain_keys/utils/__init__.py
newchain_keys/utils/address.py
newchain_keys/utils/der.py
newchain_keys/utils/module_loading.py
newchain_keys/utils/numeric.py
newchain_keys/utils/padding.py
newchain_keys-0.2.0.dist-info/LICENSE
newchain_keys-0.2.0.dist-info/METADATA
newchain_keys-0.2.0.dist-info/WHEEL
newchain_keys-0.2.0.dist-info/top_level.txt
newchain_keys-0.2.0.dist-info/RECORD
